ezpyai/__init__.py
ezpyai/_logger.py
ezpyai/constants/__init__.py
ezpyai/constants/_chat_ids.py
ezpyai/constants/_chat_roles.py
ezpyai/constants/_dict_keys.py
ezpyai/constants/_env_vars.py
ezpyai/constants/_http_content_types.py
ezpyai/constants/_http_headers.py
ezpyai/constants/_http_methods.py
ezpyai/constants/_names.py
ezpyai/exceptions/__init__.py
ezpyai/exceptions/_general.py
ezpyai/exceptions/_llm.py
ezpyai/exceptions/_llm_provider.py
ezpyai/llm/__init__.py
ezpyai/llm/conversation.py
ezpyai/llm/prompt.py
ezpyai/llm/dataset/__init__.py
ezpyai/llm/dataset/chat/__init__.py
ezpyai/llm/dataset/chat/sources/__init__.py
ezpyai/llm/dataset/chat/sources/_dataset_source.py
ezpyai/llm/dataset/chat/sources/telegram.py
ezpyai/llm/dataset/instruct/__init__.py
ezpyai/llm/dataset/instruct/instruct.py
ezpyai/llm/knowledge/__init__.py
ezpyai/llm/knowledge/_knowledge_db.py
ezpyai/llm/knowledge/_knowledge_gatherer.py
ezpyai/llm/knowledge/chroma_db.py
ezpyai/llm/knowledge/knowledge_item.py
ezpyai/llm/providers/_llm_provider.py
ezpyai/llm/providers/openai.py
ezpyai/llm/providers/text_generation_web_ui.py
ezpyai/llm/providers/_http_clients/__init__.py
ezpyai/llm/providers/_http_clients/text_generation_web_ui.py
ezpyai-0.0.1a8.dist-info/METADATA
ezpyai-0.0.1a8.dist-info/WHEEL
ezpyai-0.0.1a8.dist-info/licenses/LICENSE
ezpyai-0.0.1a8.dist-info/RECORD
