Metadata-Version: 2.3
Name: ezpyai
Version: 0.0.1a8
Summary: A useful utility library for AI applications
Project-URL: Homepage, https://github.com/psyb0t/ezpyai
Project-URL: Issues, https://github.com/psyb0t/ezpyai/issues
Author-email: Ciprian Mandache <psyb0t@51k.eu>
License-File: LICENSE
Classifier: Operating System :: OS Independent
Classifier: Programming Language :: Python :: 3
Requires-Python: >=3.8
Requires-Dist: beautifulsoup4==4.12.3
Requires-Dist: chromadb==0.5.4
Requires-Dist: openai==1.35.13
Requires-Dist: pandas==2.2.2
Requires-Dist: pypdf>=3.9.0
Requires-Dist: python-docx==1.1.2
Requires-Dist: python-magic==0.4.27
